professionals/__init__.py
professionals/professionals.py
professionals-0.0.4.dist-info/LICENSE
professionals-0.0.4.dist-info/METADATA
professionals-0.0.4.dist-info/WHEEL
professionals-0.0.4.dist-info/top_level.txt
professionals-0.0.4.dist-info/RECORD
