Metadata-Version: 2.1
Name: professionals
Version: 0.0.4
Summary: Data structures and functions to work with professional data.
Home-page: https://github.com/professional-app/lib_sdk
Author: Professional App
Author-email: support@professional.app
License: UNKNOWN
Project-URL: Bug Tracker, https://github.com/professional-app/lib_sdk/issues
Platform: UNKNOWN
Classifier: Development Status :: 3 - Alpha
Classifier: Programming Language :: Python :: 3
Classifier: License :: OSI Approved :: MIT License
Classifier: Operating System :: OS Independent
Requires-Python: >=3.6
License-File: LICENSE
Requires-Dist: esam
